{
  "name": "bugtrack",
  "project": "std",
  "extends": null,
  "start": "new",
  "states": [
    {
      "id": "new",
      "caption": "New",
      "closed": false,
      "transitions": [
        "assigned",
        "in_progress"
      ],
      "actions": []
    },
    {
      "id": "assigned",
      "caption": "Assigned",
      "closed": false,
      "transitions": [
        "new",
        "in_progress",
        "needs_more_info",
        "review",
        "qa",
        "verified",
        "duplicate",
        "working_as_intended",
        "deferred"
      ],
      "actions": []
    },
    {
      "id": "in_progress",
      "caption": "In Progress",
      "closed": false,
      "transitions": [
        "new",
        "assigned",
        "needs_more_info",
        "review",
        "qa",
        "verified",
        "duplicate",
        "working_as_intended",
        "deferred",
        "cannot_reproduce"
      ],
      "actions": []
    },
    {
      "id": "needs_more_info",
      "caption": "Needs More Information",
      "closed": false,
      "transitions": [
        "assigned",
        "verified",
        "duplicate",
        "working_as_intended",
        "deferred",
        "cannot_reproduce"
      ],
      "actions": []
    },
    {
      "id": "review",
      "caption": "In Review",
      "closed": false,
      "transitions": [
        "assigned",
        "in_progress",
        "qa",
        "verified"
      ],
      "actions": []
    },
    {
      "id": "qa",
      "caption": "In QA",
      "closed": false,
      "transitions": [
        "assigned",
        "in_progress",
        "verified"
      ],
      "actions": {
        "owner": "{reporter}"
      }
    },
    {
      "id": "verified",
      "caption": "Verified",
      "closed": true,
      "transitions": [
        "assigned",
        "in_progress"
      ],
      "actions": {
        "owner": null
      }
    },
    {
      "id": "duplicate",
      "caption": "Duplicate",
      "closed": true,
      "transitions": [
        "assigned",
        "in_progress"
      ],
      "actions": []
    },
    {
      "id": "working_as_intended",
      "caption": "Working As Intended",
      "closed": true,
      "transitions": [
        "assigned",
        "in_progress"
      ],
      "actions": []
    },
    {
      "id": "deferred",
      "caption": "Deferred",
      "closed": true,
      "transitions": [
        "assigned",
        "in_progress"
      ],
      "actions": []
    },
    {
      "id": "cannot_reproduce",
      "caption": "Cannot Reproduce",
      "closed": true,
      "transitions": [
        "assigned",
        "in_progress"
      ],
      "actions": []
    }
  ]
}
